[
	{
		"score": 0.545782985713552,
		"keypoints": [
			{
				"score": 0.9981837868690491,
				"part": "nose",
				"position": {
					"x": 98.48018056338594,
					"y": 101.08932400732924
				}
			},
			{
				"score": 0.9977105855941772,
				"part": "leftEye",
				"position": {
					"x": 110.43716902585372,
					"y": 90.91803041438466
				}
			},
			{
				"score": 0.9976696372032166,
				"part": "rightEye",
				"position": {
					"x": 85.288019239288,
					"y": 92.8403030867429
				}
			},
			{
				"score": 0.8859493732452393,
				"part": "leftEar",
				"position": {
					"x": 128.93905671109857,
					"y": 94.98350163096005
				}
			},
			{
				"score": 0.8993870615959167,
				"part": "rightEar",
				"position": {
					"x": 75.45706019450708,
					"y": 93.1890328004188
				}
			},
			{
				"score": 0.9945238828659058,
				"part": "leftShoulder",
				"position": {
					"x": 164.38391239126932,
					"y": 152.70229945231958
				}
			},
			{
				"score": 0.9882954359054565,
				"part": "rightShoulder",
				"position": {
					"x": 48.052597203205536,
					"y": 146.8764157639336
				}
			},
			{
				"score": 0.811634361743927,
				"part": "leftElbow",
				"position": {
					"x": 208.90239157135952,
					"y": 229.22036585856958
				}
			},
			{
				"score": 0.30217504501342773,
				"part": "rightElbow",
				"position": {
					"x": 18.227164042364688,
					"y": 157.69612798002575
				}
			},
			{
				"score": 0.25332775712013245,
				"part": "leftWrist",
				"position": {
					"x": -4.2482147216796875,
					"y": 119.57589249758375
				}
			},
			{
				"score": 0.569870114326477,
				"part": "rightWrist",
				"position": {
					"x": -2.918858872246496,
					"y": 120.4428761275773
				}
			},
			{
				"score": 0.20115214586257935,
				"part": "leftHip",
				"position": {
					"x": 28.820656058714558,
					"y": 226.49749567090848
				}
			},
			{
				"score": 0.1378682553768158,
				"part": "rightHip",
				"position": {
					"x": 33.76546800751047,
					"y": 197.22264618234533
				}
			},
			{
				"score": 0.06483548134565353,
				"part": "leftKnee",
				"position": {
					"x": 21.223361615053154,
					"y": 196.40337316768685
				}
			},
			{
				"score": 0.0868988111615181,
				"part": "rightKnee",
				"position": {
					"x": 32.06800826554446,
					"y": 197.00095391027705
				}
			},
			{
				"score": 0.04492756351828575,
				"part": "leftAnkle",
				"position": {
					"x": 13.581267995932667,
					"y": 226.96119422519328
				}
			},
			{
				"score": 0.043901458382606506,
				"part": "rightAnkle",
				"position": {
					"x": 18.191372271665593,
					"y": 227.6803066607603
				}
			}
		]
	}
]